{
  "lastRun": "2026-06-20T15:39:10.899Z",
  "success": false,
  "postsCount": 0,
  "sourcesCount": 4,
  "errors": [
    {
      "source": "reddit_steamdeals",
      "message": "[fetchReddit(steamdeals)] Failed after 3 attempts: Status code 429",
      "time": "2026-06-20T15:39:07.217Z"
    },
    {
      "source": "reddit_gamingnews",
      "message": "[fetchReddit(gamingnews)] Failed after 3 attempts: Status code 429",
      "time": "2026-06-20T15:39:10.899Z"
    }
  ],
  "nextRun": "2026-06-20T16:39:10.899Z"
}